attrs_mate/__init__.py
attrs_mate/_version.py
attrs_mate/mate.py
attrs_mate-1.1.2.dist-info/AUTHORS.rst
attrs_mate-1.1.2.dist-info/LICENSE.txt
attrs_mate-1.1.2.dist-info/METADATA
attrs_mate-1.1.2.dist-info/WHEEL
attrs_mate-1.1.2.dist-info/top_level.txt
attrs_mate-1.1.2.dist-info/RECORD
